application_file_scanner/.external-package
application_file_scanner/__init__.py
application_file_scanner/application_file_scanner.py
application_file_scanner/git_processor.py
application_file_scanner/py.typed
application_file_scanner/version.py
application_file_scanner-0.6.3.dist-info/licenses/LICENSE.txt
application_file_scanner-0.6.3.dist-info/METADATA
application_file_scanner-0.6.3.dist-info/WHEEL
application_file_scanner-0.6.3.dist-info/top_level.txt
application_file_scanner-0.6.3.dist-info/RECORD
