Metadata-Version: 2.4
Name: application_file_scanner
Version: 0.6.3
Summary: A small package to deal with the headaches of scanning for files for an application to execute on.
Home-page: https://github.com/jackdewinter/application_file_scanner
Author: Jack De Winter
Author-email: jack.de.winter@outlook.com
Maintainer: Jack De Winter
Maintainer-email: jack.de.winter@outlook.com
License: MIT
Project-URL: Documentation, https://application_file_scanner.readthedocs.io/
Project-URL: Change Log, https://application_file_scanner.readthedocs.io/en/latest/changelog/
Keywords: properties
Classifier: Development Status :: 4 - Beta
Classifier: Environment :: Console
Classifier: Intended Audience :: Developers
Classifier: Programming Language :: Python :: 3.10
Classifier: Programming Language :: Python :: 3.11
Classifier: Programming Language :: Python :: 3.12
Classifier: Programming Language :: Python :: 3.13
Classifier: License :: OSI Approved :: MIT License
Classifier: Operating System :: OS Independent
Classifier: Natural Language :: English
Classifier: Topic :: Software Development :: Libraries :: Application Frameworks
Requires-Python: >=3.10.0
License-File: LICENSE.txt
Requires-Dist: typing-extensions>=4.5.0
Requires-Dist: py-walk>=0.3.3
Dynamic: author
Dynamic: author-email
Dynamic: classifier
Dynamic: description
Dynamic: description-content-type
Dynamic: home-page
Dynamic: keywords
Dynamic: license
Dynamic: license-file
Dynamic: maintainer
Dynamic: maintainer-email
Dynamic: project-url
Dynamic: requires-dist
Dynamic: requires-python
Dynamic: summary
